{
  "page": 380,
  "lines": [
    {
      "line": 1,
      "type": "text",
      "text": "فَلَمَّا جَآءَ سُلَيْمَـٰنَ قَالَ أَتُمِدُّونَنِ بِمَالٍۢ فَمَآ ءَاتَىٰنِۦَ ٱللَّهُ خَيْرٌۭ مِّمَّآ",
      "verseRange": "27:36-27:36",
      "words": [
        {
          "location": "27:36:1",
          "word": "فَلَمَّا",
          "qpcV1": "ﭑ",
          "qpcV2": "ﱁ"
        },
        {
          "location": "27:36:2",
          "word": "جَآءَ",
          "qpcV1": "ﭒ",
          "qpcV2": "ﱂ"
        },
        {
          "location": "27:36:3",
          "word": "سُلَيْمَـٰنَ",
          "qpcV1": "ﭓ",
          "qpcV2": "ﱃ"
        },
        {
          "location": "27:36:4",
          "word": "قَالَ",
          "qpcV1": "ﭔ",
          "qpcV2": "ﱄ"
        },
        {
          "location": "27:36:5",
          "word": "أَتُمِدُّونَنِ",
          "qpcV1": "ﭕ",
          "qpcV2": "ﱅ"
        },
        {
          "location": "27:36:6",
          "word": "بِمَالٍۢ",
          "qpcV1": "ﭖ",
          "qpcV2": "ﱆ"
        },
        {
          "location": "27:36:7",
          "word": "فَمَآ",
          "qpcV1": "ﭗ",
          "qpcV2": "ﱇ"
        },
        {
          "location": "27:36:8",
          "word": "ءَاتَىٰنِۦَ",
          "qpcV1": "ﭘ",
          "qpcV2": "ﱈ"
        },
        {
          "location": "27:36:9",
          "word": "ٱللَّهُ",
          "qpcV1": "ﭙ",
          "qpcV2": "ﱉ"
        },
        {
          "location": "27:36:10",
          "word": "خَيْرٌۭ",
          "qpcV1": "ﭚ",
          "qpcV2": "ﱊ"
        },
        {
          "location": "27:36:11",
          "word": "مِّمَّآ",
          "qpcV1": "ﭛ",
          "qpcV2": "ﱋ"
        }
      ]
    },
    {
      "line": 2,
      "type": "text",
      "text": "ءَاتَىٰكُم بَلْ أَنتُم بِهَدِيَّتِكُمْ تَفْرَحُونَ ٣٦ ٱرْجِعْ إِلَيْهِمْ فَلَنَأْتِيَنَّهُم",
      "verseRange": "27:36-27:37",
      "words": [
        {
          "location": "27:36:12",
          "word": "ءَاتَىٰكُم",
          "qpcV1": "ﭜ",
          "qpcV2": "ﱌﱍ"
        },
        {
          "location": "27:36:13",
          "word": "بَلْ",
          "qpcV1": "ﭝ",
          "qpcV2": "ﱎ"
        },
        {
          "location": "27:36:14",
          "word": "أَنتُم",
          "qpcV1": "ﭞ",
          "qpcV2": "ﱏ"
        },
        {
          "location": "27:36:15",
          "word": "بِهَدِيَّتِكُمْ",
          "qpcV1": "ﭟ",
          "qpcV2": "ﱐ"
        },
        {
          "location": "27:36:16",
          "word": "تَفْرَحُونَ ٣٦",
          "qpcV1": "ﭠ ﭡ",
          "qpcV2": "ﱑ ﱒ"
        },
        {
          "location": "27:37:1",
          "word": "ٱرْجِعْ",
          "qpcV1": "ﭢ",
          "qpcV2": "ﱓ"
        },
        {
          "location": "27:37:2",
          "word": "إِلَيْهِمْ",
          "qpcV1": "ﭣ",
          "qpcV2": "ﱔ"
        },
        {
          "location": "27:37:3",
          "word": "فَلَنَأْتِيَنَّهُم",
          "qpcV1": "ﭤ",
          "qpcV2": "ﱕ"
        }
      ]
    },
    {
      "line": 3,
      "type": "text",
      "text": "بِجُنُودٍۢ لَّا قِبَلَ لَهُم بِهَا وَلَنُخْرِجَنَّهُم مِّنْهَآ أَذِلَّةًۭ وَهُمْ صَـٰغِرُونَ ٣٧ قَالَ",
      "verseRange": "27:37-27:38",
      "words": [
        {
          "location": "27:37:4",
          "word": "بِجُنُودٍۢ",
          "qpcV1": "ﭥ",
          "qpcV2": "ﱖ"
        },
        {
          "location": "27:37:5",
          "word": "لَّا",
          "qpcV1": "ﭦ",
          "qpcV2": "ﱗ"
        },
        {
          "location": "27:37:6",
          "word": "قِبَلَ",
          "qpcV1": "ﭧ",
          "qpcV2": "ﱘ"
        },
        {
          "location": "27:37:7",
          "word": "لَهُم",
          "qpcV1": "ﭨ",
          "qpcV2": "ﱙ"
        },
        {
          "location": "27:37:8",
          "word": "بِهَا",
          "qpcV1": "ﭩ",
          "qpcV2": "ﱚ"
        },
        {
          "location": "27:37:9",
          "word": "وَلَنُخْرِجَنَّهُم",
          "qpcV1": "ﭪ",
          "qpcV2": "ﱛ"
        },
        {
          "location": "27:37:10",
          "word": "مِّنْهَآ",
          "qpcV1": "ﭫ",
          "qpcV2": "ﱜ"
        },
        {
          "location": "27:37:11",
          "word": "أَذِلَّةًۭ",
          "qpcV1": "ﭬ",
          "qpcV2": "ﱝ"
        },
        {
          "location": "27:37:12",
          "word": "وَهُمْ",
          "qpcV1": "ﭭ",
          "qpcV2": "ﱞ"
        },
        {
          "location": "27:37:13",
          "word": "صَـٰغِرُونَ ٣٧",
          "qpcV1": "ﭮ ﭯ",
          "qpcV2": "ﱟ ﱠ"
        },
        {
          "location": "27:38:1",
          "word": "قَالَ",
          "qpcV1": "ﭰ",
          "qpcV2": "ﱡ"
        }
      ]
    },
    {
      "line": 4,
      "type": "text",
      "text": "يَـٰٓأَيُّهَا ٱلْمَلَؤُا۟ أَيُّكُمْ يَأْتِينِى بِعَرْشِهَا قَبْلَ أَن يَأْتُونِى مُسْلِمِينَ ٣٨",
      "verseRange": "27:38-27:38",
      "words": [
        {
          "location": "27:38:2",
          "word": "يَـٰٓأَيُّهَا",
          "qpcV1": "ﭱ",
          "qpcV2": "ﱢ"
        },
        {
          "location": "27:38:3",
          "word": "ٱلْمَلَؤُا۟",
          "qpcV1": "ﭲ",
          "qpcV2": "ﱣ"
        },
        {
          "location": "27:38:4",
          "word": "أَيُّكُمْ",
          "qpcV1": "ﭳ",
          "qpcV2": "ﱤ"
        },
        {
          "location": "27:38:5",
          "word": "يَأْتِينِى",
          "qpcV1": "ﭴ",
          "qpcV2": "ﱥ"
        },
        {
          "location": "27:38:6",
          "word": "بِعَرْشِهَا",
          "qpcV1": "ﭵ",
          "qpcV2": "ﱦ"
        },
        {
          "location": "27:38:7",
          "word": "قَبْلَ",
          "qpcV1": "ﭶ",
          "qpcV2": "ﱧ"
        },
        {
          "location": "27:38:8",
          "word": "أَن",
          "qpcV1": "ﭷ",
          "qpcV2": "ﱨ"
        },
        {
          "location": "27:38:9",
          "word": "يَأْتُونِى",
          "qpcV1": "ﭸ",
          "qpcV2": "ﱩ"
        },
        {
          "location": "27:38:10",
          "word": "مُسْلِمِينَ ٣٨",
          "qpcV1": "ﭹ ﭺ",
          "qpcV2": "ﱪ ﱫ"
        }
      ]
    },
    {
      "line": 5,
      "type": "text",
      "text": "قَالَ عِفْرِيتٌۭ مِّنَ ٱلْجِنِّ أَنَا۠ ءَاتِيكَ بِهِۦ قَبْلَ أَن تَقُومَ مِن مَّقَامِكَ ۖ وَإِنِّى",
      "verseRange": "27:39-27:39",
      "words": [
        {
          "location": "27:39:1",
          "word": "قَالَ",
          "qpcV1": "ﭻ",
          "qpcV2": "ﱬ"
        },
        {
          "location": "27:39:2",
          "word": "عِفْرِيتٌۭ",
          "qpcV1": "ﭼ",
          "qpcV2": "ﱭ"
        },
        {
          "location": "27:39:3",
          "word": "مِّنَ",
          "qpcV1": "ﭽ",
          "qpcV2": "ﱮ"
        },
        {
          "location": "27:39:4",
          "word": "ٱلْجِنِّ",
          "qpcV1": "ﭾ",
          "qpcV2": "ﱯ"
        },
        {
          "location": "27:39:5",
          "word": "أَنَا۠",
          "qpcV1": "ﭿ",
          "qpcV2": "ﱰ"
        },
        {
          "location": "27:39:6",
          "word": "ءَاتِيكَ",
          "qpcV1": "ﮀ",
          "qpcV2": "ﱱ"
        },
        {
          "location": "27:39:7",
          "word": "بِهِۦ",
          "qpcV1": "ﮁ",
          "qpcV2": "ﱲ"
        },
        {
          "location": "27:39:8",
          "word": "قَبْلَ",
          "qpcV1": "ﮂ",
          "qpcV2": "ﱳ"
        },
        {
          "location": "27:39:9",
          "word": "أَن",
          "qpcV1": "ﮃ",
          "qpcV2": "ﱴ"
        },
        {
          "location": "27:39:10",
          "word": "تَقُومَ",
          "qpcV1": "ﮄ",
          "qpcV2": "ﱵ"
        },
        {
          "location": "27:39:11",
          "word": "مِن",
          "qpcV1": "ﮅ",
          "qpcV2": "ﱶ"
        },
        {
          "location": "27:39:12",
          "word": "مَّقَامِكَ ۖ",
          "qpcV1": "ﮆﮇ",
          "qpcV2": "ﱷﱸ"
        },
        {
          "location": "27:39:13",
          "word": "وَإِنِّى",
          "qpcV1": "ﮈ",
          "qpcV2": "ﱹ"
        }
      ]
    },
    {
      "line": 6,
      "type": "text",
      "text": "عَلَيْهِ لَقَوِىٌّ أَمِينٌۭ ٣٩ قَالَ ٱلَّذِى عِندَهُۥ عِلْمٌۭ مِّنَ ٱلْكِتَـٰبِ أَنَا۠ ءَاتِيكَ",
      "verseRange": "27:39-27:40",
      "words": [
        {
          "location": "27:39:14",
          "word": "عَلَيْهِ",
          "qpcV1": "ﮉ",
          "qpcV2": "ﱺ"
        },
        {
          "location": "27:39:15",
          "word": "لَقَوِىٌّ",
          "qpcV1": "ﮊ",
          "qpcV2": "ﱻ"
        },
        {
          "location": "27:39:16",
          "word": "أَمِينٌۭ ٣٩",
          "qpcV1": "ﮋ ﮌ",
          "qpcV2": "ﱼ ﱽ"
        },
        {
          "location": "27:40:1",
          "word": "قَالَ",
          "qpcV1": "ﮍ",
          "qpcV2": "ﱾ"
        },
        {
          "location": "27:40:2",
          "word": "ٱلَّذِى",
          "qpcV1": "ﮎ",
          "qpcV2": "ﱿ"
        },
        {
          "location": "27:40:3",
          "word": "عِندَهُۥ",
          "qpcV1": "ﮏ",
          "qpcV2": "ﲀ"
        },
        {
          "location": "27:40:4",
          "word": "عِلْمٌۭ",
          "qpcV1": "ﮐ",
          "qpcV2": "ﲁ"
        },
        {
          "location": "27:40:5",
          "word": "مِّنَ",
          "qpcV1": "ﮑ",
          "qpcV2": "ﲂ"
        },
        {
          "location": "27:40:6",
          "word": "ٱلْكِتَـٰبِ",
          "qpcV1": "ﮒ",
          "qpcV2": "ﲃ"
        },
        {
          "location": "27:40:7",
          "word": "أَنَا۠",
          "qpcV1": "ﮓ",
          "qpcV2": "ﲄ"
        },
        {
          "location": "27:40:8",
          "word": "ءَاتِيكَ",
          "qpcV1": "ﮔ",
          "qpcV2": "ﲅ"
        }
      ]
    },
    {
      "line": 7,
      "type": "text",
      "text": "بِهِۦ قَبْلَ أَن يَرْتَدَّ إِلَيْكَ طَرْفُكَ ۚ فَلَمَّا رَءَاهُ مُسْتَقِرًّا عِندَهُۥ قَالَ هَـٰذَا",
      "verseRange": "27:40-27:40",
      "words": [
        {
          "location": "27:40:9",
          "word": "بِهِۦ",
          "qpcV1": "ﮕ",
          "qpcV2": "ﲆ"
        },
        {
          "location": "27:40:10",
          "word": "قَبْلَ",
          "qpcV1": "ﮖ",
          "qpcV2": "ﲇ"
        },
        {
          "location": "27:40:11",
          "word": "أَن",
          "qpcV1": "ﮗ",
          "qpcV2": "ﲈ"
        },
        {
          "location": "27:40:12",
          "word": "يَرْتَدَّ",
          "qpcV1": "ﮘ",
          "qpcV2": "ﲉ"
        },
        {
          "location": "27:40:13",
          "word": "إِلَيْكَ",
          "qpcV1": "ﮙ",
          "qpcV2": "ﲊ"
        },
        {
          "location": "27:40:14",
          "word": "طَرْفُكَ ۚ",
          "qpcV1": "ﮚﮛ",
          "qpcV2": "ﲋﲌ"
        },
        {
          "location": "27:40:15",
          "word": "فَلَمَّا",
          "qpcV1": "ﮜ",
          "qpcV2": "ﲍ"
        },
        {
          "location": "27:40:16",
          "word": "رَءَاهُ",
          "qpcV1": "ﮝ",
          "qpcV2": "ﲎ"
        },
        {
          "location": "27:40:17",
          "word": "مُسْتَقِرًّا",
          "qpcV1": "ﮞ",
          "qpcV2": "ﲏ"
        },
        {
          "location": "27:40:18",
          "word": "عِندَهُۥ",
          "qpcV1": "ﮟ",
          "qpcV2": "ﲐ"
        },
        {
          "location": "27:40:19",
          "word": "قَالَ",
          "qpcV1": "ﮠ",
          "qpcV2": "ﲑ"
        },
        {
          "location": "27:40:20",
          "word": "هَـٰذَا",
          "qpcV1": "ﮡ",
          "qpcV2": "ﲒ"
        }
      ]
    },
    {
      "line": 8,
      "type": "text",
      "text": "مِن فَضْلِ رَبِّى لِيَبْلُوَنِىٓ ءَأَشْكُرُ أَمْ أَكْفُرُ ۖ وَمَن شَكَرَ فَإِنَّمَا يَشْكُرُ",
      "verseRange": "27:40-27:40",
      "words": [
        {
          "location": "27:40:21",
          "word": "مِن",
          "qpcV1": "ﮢ",
          "qpcV2": "ﲓ"
        },
        {
          "location": "27:40:22",
          "word": "فَضْلِ",
          "qpcV1": "ﮣ",
          "qpcV2": "ﲔ"
        },
        {
          "location": "27:40:23",
          "word": "رَبِّى",
          "qpcV1": "ﮤ",
          "qpcV2": "ﲕ"
        },
        {
          "location": "27:40:24",
          "word": "لِيَبْلُوَنِىٓ",
          "qpcV1": "ﮥ",
          "qpcV2": "ﲖ"
        },
        {
          "location": "27:40:25",
          "word": "ءَأَشْكُرُ",
          "qpcV1": "ﮦ",
          "qpcV2": "ﲗ"
        },
        {
          "location": "27:40:26",
          "word": "أَمْ",
          "qpcV1": "ﮧ",
          "qpcV2": "ﲘ"
        },
        {
          "location": "27:40:27",
          "word": "أَكْفُرُ ۖ",
          "qpcV1": "ﮨﮩ",
          "qpcV2": "ﲙﲚ"
        },
        {
          "location": "27:40:28",
          "word": "وَمَن",
          "qpcV1": "ﮪ",
          "qpcV2": "ﲛ"
        },
        {
          "location": "27:40:29",
          "word": "شَكَرَ",
          "qpcV1": "ﮫ",
          "qpcV2": "ﲜ"
        },
        {
          "location": "27:40:30",
          "word": "فَإِنَّمَا",
          "qpcV1": "ﮬ",
          "qpcV2": "ﲝ"
        },
        {
          "location": "27:40:31",
          "word": "يَشْكُرُ",
          "qpcV1": "ﮭ",
          "qpcV2": "ﲞ"
        }
      ]
    },
    {
      "line": 9,
      "type": "text",
      "text": "لِنَفْسِهِۦ ۖ وَمَن كَفَرَ فَإِنَّ رَبِّى غَنِىٌّۭ كَرِيمٌۭ ٤٠ قَالَ نَكِّرُوا۟ لَهَا عَرْشَهَا",
      "verseRange": "27:40-27:41",
      "words": [
        {
          "location": "27:40:32",
          "word": "لِنَفْسِهِۦ ۖ",
          "qpcV1": "ﮮﮯ",
          "qpcV2": "ﲟﲠ"
        },
        {
          "location": "27:40:33",
          "word": "وَمَن",
          "qpcV1": "ﮰ",
          "qpcV2": "ﲡ"
        },
        {
          "location": "27:40:34",
          "word": "كَفَرَ",
          "qpcV1": "ﮱ",
          "qpcV2": "ﲢ"
        },
        {
          "location": "27:40:35",
          "word": "فَإِنَّ",
          "qpcV1": "ﯓ",
          "qpcV2": "ﲣ"
        },
        {
          "location": "27:40:36",
          "word": "رَبِّى",
          "qpcV1": "ﯔ",
          "qpcV2": "ﲤ"
        },
        {
          "location": "27:40:37",
          "word": "غَنِىٌّۭ",
          "qpcV1": "ﯕ",
          "qpcV2": "ﲥ"
        },
        {
          "location": "27:40:38",
          "word": "كَرِيمٌۭ ٤٠",
          "qpcV1": "ﯖ ﯗ",
          "qpcV2": "ﲦ ﲧ"
        },
        {
          "location": "27:41:1",
          "word": "قَالَ",
          "qpcV1": "ﯘ",
          "qpcV2": "ﲨ"
        },
        {
          "location": "27:41:2",
          "word": "نَكِّرُوا۟",
          "qpcV1": "ﯙ",
          "qpcV2": "ﲩ"
        },
        {
          "location": "27:41:3",
          "word": "لَهَا",
          "qpcV1": "ﯚ",
          "qpcV2": "ﲪ"
        },
        {
          "location": "27:41:4",
          "word": "عَرْشَهَا",
          "qpcV1": "ﯛ",
          "qpcV2": "ﲫ"
        }
      ]
    },
    {
      "line": 10,
      "type": "text",
      "text": "نَنظُرْ أَتَهْتَدِىٓ أَمْ تَكُونُ مِنَ ٱلَّذِينَ لَا يَهْتَدُونَ ٤١ فَلَمَّا جَآءَتْ قِيلَ",
      "verseRange": "27:41-27:42",
      "words": [
        {
          "location": "27:41:5",
          "word": "نَنظُرْ",
          "qpcV1": "ﯜ",
          "qpcV2": "ﲬ"
        },
        {
          "location": "27:41:6",
          "word": "أَتَهْتَدِىٓ",
          "qpcV1": "ﯝ",
          "qpcV2": "ﲭ"
        },
        {
          "location": "27:41:7",
          "word": "أَمْ",
          "qpcV1": "ﯞ",
          "qpcV2": "ﲮ"
        },
        {
          "location": "27:41:8",
          "word": "تَكُونُ",
          "qpcV1": "ﯟ",
          "qpcV2": "ﲯ"
        },
        {
          "location": "27:41:9",
          "word": "مِنَ",
          "qpcV1": "ﯠ",
          "qpcV2": "ﲰ"
        },
        {
          "location": "27:41:10",
          "word": "ٱلَّذِينَ",
          "qpcV1": "ﯡ",
          "qpcV2": "ﲱ"
        },
        {
          "location": "27:41:11",
          "word": "لَا",
          "qpcV1": "ﯢ",
          "qpcV2": "ﲲ"
        },
        {
          "location": "27:41:12",
          "word": "يَهْتَدُونَ ٤١",
          "qpcV1": "ﯣ ﯤ",
          "qpcV2": "ﲳ ﲴ"
        },
        {
          "location": "27:42:1",
          "word": "فَلَمَّا",
          "qpcV1": "ﯥ",
          "qpcV2": "ﲵ"
        },
        {
          "location": "27:42:2",
          "word": "جَآءَتْ",
          "qpcV1": "ﯦ",
          "qpcV2": "ﲶ"
        },
        {
          "location": "27:42:3",
          "word": "قِيلَ",
          "qpcV1": "ﯧ",
          "qpcV2": "ﲷ"
        }
      ]
    },
    {
      "line": 11,
      "type": "text",
      "text": "أَهَـٰكَذَا عَرْشُكِ ۖ قَالَتْ كَأَنَّهُۥ هُوَ ۚ وَأُوتِينَا ٱلْعِلْمَ مِن قَبْلِهَا وَكُنَّا مُسْلِمِينَ",
      "verseRange": "27:42-27:42",
      "words": [
        {
          "location": "27:42:4",
          "word": "أَهَـٰكَذَا",
          "qpcV1": "ﯨ",
          "qpcV2": "ﲸ"
        },
        {
          "location": "27:42:5",
          "word": "عَرْشُكِ ۖ",
          "qpcV1": "ﯩﯪ",
          "qpcV2": "ﲹﲺ"
        },
        {
          "location": "27:42:6",
          "word": "قَالَتْ",
          "qpcV1": "ﯫ",
          "qpcV2": "ﲻ"
        },
        {
          "location": "27:42:7",
          "word": "كَأَنَّهُۥ",
          "qpcV1": "ﯬ",
          "qpcV2": "ﲼ"
        },
        {
          "location": "27:42:8",
          "word": "هُوَ ۚ",
          "qpcV1": "ﯭﯮ",
          "qpcV2": "ﲽﲾ"
        },
        {
          "location": "27:42:9",
          "word": "وَأُوتِينَا",
          "qpcV1": "ﯯ",
          "qpcV2": "ﲿ"
        },
        {
          "location": "27:42:10",
          "word": "ٱلْعِلْمَ",
          "qpcV1": "ﯰ",
          "qpcV2": "ﳀ"
        },
        {
          "location": "27:42:11",
          "word": "مِن",
          "qpcV1": "ﯱ",
          "qpcV2": "ﳁ"
        },
        {
          "location": "27:42:12",
          "word": "قَبْلِهَا",
          "qpcV1": "ﯲ",
          "qpcV2": "ﳂ"
        },
        {
          "location": "27:42:13",
          "word": "وَكُنَّا",
          "qpcV1": "ﯳ",
          "qpcV2": "ﳃ"
        },
        {
          "location": "27:42:14",
          "word": "مُسْلِمِينَ",
          "qpcV1": "ﯴ",
          "qpcV2": "ﳄ"
        }
      ]
    },
    {
      "line": 12,
      "type": "text",
      "text": "٤٢ وَصَدَّهَا مَا كَانَت تَّعْبُدُ مِن دُونِ ٱللَّهِ ۖ إِنَّهَا كَانَتْ مِن قَوْمٍۢ كَـٰفِرِينَ",
      "verseRange": "27:43-27:43",
      "words": [
        {
          "location": "27:42:15",
          "word": "٤٢",
          "qpcV1": "ﯵ",
          "qpcV2": "ﳅ"
        },
        {
          "location": "27:43:1",
          "word": "وَصَدَّهَا",
          "qpcV1": "ﯶ",
          "qpcV2": "ﳆ"
        },
        {
          "location": "27:43:2",
          "word": "مَا",
          "qpcV1": "ﯷ",
          "qpcV2": "ﳇ"
        },
        {
          "location": "27:43:3",
          "word": "كَانَت",
          "qpcV1": "ﯸ",
          "qpcV2": "ﳈ"
        },
        {
          "location": "27:43:4",
          "word": "تَّعْبُدُ",
          "qpcV1": "ﯹ",
          "qpcV2": "ﳉ"
        },
        {
          "location": "27:43:5",
          "word": "مِن",
          "qpcV1": "ﯺ",
          "qpcV2": "ﳊ"
        },
        {
          "location": "27:43:6",
          "word": "دُونِ",
          "qpcV1": "ﯻ",
          "qpcV2": "ﳋ"
        },
        {
          "location": "27:43:7",
          "word": "ٱللَّهِ ۖ",
          "qpcV1": "ﯼﯽ",
          "qpcV2": "ﳌﳍ"
        },
        {
          "location": "27:43:8",
          "word": "إِنَّهَا",
          "qpcV1": "ﯾ",
          "qpcV2": "ﳎ"
        },
        {
          "location": "27:43:9",
          "word": "كَانَتْ",
          "qpcV1": "ﯿ",
          "qpcV2": "ﳏ"
        },
        {
          "location": "27:43:10",
          "word": "مِن",
          "qpcV1": "ﰀ",
          "qpcV2": "ﳐ"
        },
        {
          "location": "27:43:11",
          "word": "قَوْمٍۢ",
          "qpcV1": "ﰁ",
          "qpcV2": "ﳑ"
        },
        {
          "location": "27:43:12",
          "word": "كَـٰفِرِينَ",
          "qpcV1": "ﰂ",
          "qpcV2": "ﳒ"
        }
      ]
    },
    {
      "line": 13,
      "type": "text",
      "text": "٤٣ قِيلَ لَهَا ٱدْخُلِى ٱلصَّرْحَ ۖ فَلَمَّا رَأَتْهُ حَسِبَتْهُ لُجَّةًۭ وَكَشَفَتْ عَن",
      "verseRange": "27:44-27:44",
      "words": [
        {
          "location": "27:43:13",
          "word": "٤٣",
          "qpcV1": "ﰃ",
          "qpcV2": "ﳓ"
        },
        {
          "location": "27:44:1",
          "word": "قِيلَ",
          "qpcV1": "ﰄ",
          "qpcV2": "ﳔ"
        },
        {
          "location": "27:44:2",
          "word": "لَهَا",
          "qpcV1": "ﰅ",
          "qpcV2": "ﳕ"
        },
        {
          "location": "27:44:3",
          "word": "ٱدْخُلِى",
          "qpcV1": "ﰆ",
          "qpcV2": "ﳖ"
        },
        {
          "location": "27:44:4",
          "word": "ٱلصَّرْحَ ۖ",
          "qpcV1": "ﰇﰈ",
          "qpcV2": "ﳗﳘ"
        },
        {
          "location": "27:44:5",
          "word": "فَلَمَّا",
          "qpcV1": "ﰉ",
          "qpcV2": "ﳙ"
        },
        {
          "location": "27:44:6",
          "word": "رَأَتْهُ",
          "qpcV1": "ﰊ",
          "qpcV2": "ﳚ"
        },
        {
          "location": "27:44:7",
          "word": "حَسِبَتْهُ",
          "qpcV1": "ﰋ",
          "qpcV2": "ﳛ"
        },
        {
          "location": "27:44:8",
          "word": "لُجَّةًۭ",
          "qpcV1": "ﰌ",
          "qpcV2": "ﳜ"
        },
        {
          "location": "27:44:9",
          "word": "وَكَشَفَتْ",
          "qpcV1": "ﰍ",
          "qpcV2": "ﳝ"
        },
        {
          "location": "27:44:10",
          "word": "عَن",
          "qpcV1": "ﰎ",
          "qpcV2": "ﳞ"
        }
      ]
    },
    {
      "line": 14,
      "type": "text",
      "text": "سَاقَيْهَا ۚ قَالَ إِنَّهُۥ صَرْحٌۭ مُّمَرَّدٌۭ مِّن قَوَارِيرَ ۗ قَالَتْ رَبِّ إِنِّى",
      "verseRange": "27:44-27:44",
      "words": [
        {
          "location": "27:44:11",
          "word": "سَاقَيْهَا ۚ",
          "qpcV1": "ﰏﰐ",
          "qpcV2": "ﳟﳠ"
        },
        {
          "location": "27:44:12",
          "word": "قَالَ",
          "qpcV1": "ﰑ",
          "qpcV2": "ﳡ"
        },
        {
          "location": "27:44:13",
          "word": "إِنَّهُۥ",
          "qpcV1": "ﰒ",
          "qpcV2": "ﳢ"
        },
        {
          "location": "27:44:14",
          "word": "صَرْحٌۭ",
          "qpcV1": "ﰓ",
          "qpcV2": "ﳣ"
        },
        {
          "location": "27:44:15",
          "word": "مُّمَرَّدٌۭ",
          "qpcV1": "ﰔ",
          "qpcV2": "ﳤ"
        },
        {
          "location": "27:44:16",
          "word": "مِّن",
          "qpcV1": "ﰕ",
          "qpcV2": "ﳥ"
        },
        {
          "location": "27:44:17",
          "word": "قَوَارِيرَ ۗ",
          "qpcV1": "ﰖﰗ",
          "qpcV2": "ﳦﳧ"
        },
        {
          "location": "27:44:18",
          "word": "قَالَتْ",
          "qpcV1": "ﰘ",
          "qpcV2": "ﳨ"
        },
        {
          "location": "27:44:19",
          "word": "رَبِّ",
          "qpcV1": "ﰙ",
          "qpcV2": "ﳩ"
        },
        {
          "location": "27:44:20",
          "word": "إِنِّى",
          "qpcV1": "ﰚ",
          "qpcV2": "ﳪ"
        }
      ]
    },
    {
      "line": 15,
      "type": "text",
      "text": "ظَلَمْتُ نَفْسِى وَأَسْلَمْتُ مَعَ سُلَيْمَـٰنَ لِلَّهِ رَبِّ ٱلْعَـٰلَمِينَ ٤٤",
      "verseRange": "27:44-27:44",
      "words": [
        {
          "location": "27:44:21",
          "word": "ظَلَمْتُ",
          "qpcV1": "ﰛ",
          "qpcV2": "ﳫ"
        },
        {
          "location": "27:44:22",
          "word": "نَفْسِى",
          "qpcV1": "ﰜ",
          "qpcV2": "ﳬ"
        },
        {
          "location": "27:44:23",
          "word": "وَأَسْلَمْتُ",
          "qpcV1": "ﰝ",
          "qpcV2": "ﳭ"
        },
        {
          "location": "27:44:24",
          "word": "مَعَ",
          "qpcV1": "ﰞ",
          "qpcV2": "ﳮ"
        },
        {
          "location": "27:44:25",
          "word": "سُلَيْمَـٰنَ",
          "qpcV1": "ﰟ",
          "qpcV2": "ﳯ"
        },
        {
          "location": "27:44:26",
          "word": "لِلَّهِ",
          "qpcV1": "ﰠ",
          "qpcV2": "ﳰ"
        },
        {
          "location": "27:44:27",
          "word": "رَبِّ",
          "qpcV1": "ﰡ",
          "qpcV2": "ﳱ"
        },
        {
          "location": "27:44:28",
          "word": "ٱلْعَـٰلَمِينَ ٤٤",
          "qpcV1": "ﰢ ﰣ",
          "qpcV2": "ﳲ ﳳ"
        }
      ]
    }
  ]
}
